README.md
setup.py
asttools/__init__.py
asttools/utils.py
asttools.egg-info/PKG-INFO
asttools.egg-info/SOURCES.txt
asttools.egg-info/dependency_links.txt
asttools.egg-info/requires.txt
asttools.egg-info/top_level.txt