Metadata-Version: 1.1
Name: asttools
Version: 0.1.4
Summary: Tools for AST construction and manipulation
Home-page: https://github.com/hchasestevens/asttools
Author: H. Chase Stevens
Author-email: chase@chasestevens.com
License: MIT
Keywords: ast asts syntax metaprogramming
Platform: UNKNOWN
Classifier: Development Status :: 3 - Alpha
Classifier: Programming Language :: Python
Classifier: Programming Language :: Python :: 2
Classifier: Programming Language :: Python :: 2.7
Classifier: Intended Audience :: Developers
Classifier: Operating System :: OS Independent
Classifier: License :: OSI Approved :: MIT License
Classifier: Natural Language :: English
